sshfs/__init__.py
sshfs/config.py
sshfs/file.py
sshfs/spec.py
sshfs/utils.py
sshfs/pools/__init__.py
sshfs/pools/base.py
sshfs/pools/hard.py
sshfs/pools/soft.py
sshfs-2025.11.0.dist-info/LICENSE
sshfs-2025.11.0.dist-info/METADATA
sshfs-2025.11.0.dist-info/WHEEL
sshfs-2025.11.0.dist-info/entry_points.txt
sshfs-2025.11.0.dist-info/top_level.txt
sshfs-2025.11.0.dist-info/RECORD
