Metadata-Version: 2.1
Name: sshfs
Version: 2025.11.0
Summary: SSH Filesystem -- Async SSH/SFTP backend for fsspec
License: Apache License 2.0
Classifier: Development Status :: 4 - Beta
Classifier: Programming Language :: Python :: 3
Classifier: Programming Language :: Python :: 3.8
Classifier: Programming Language :: Python :: 3.9
Classifier: Programming Language :: Python :: 3.10
Classifier: Programming Language :: Python :: 3.11
Classifier: Programming Language :: Python :: 3.12
Classifier: Programming Language :: Python :: 3.13
Classifier: Programming Language :: Python :: 3.14
License-File: LICENSE
Requires-Dist: fsspec>=2021.8.1
Requires-Dist: asyncssh<3,>=2.11.0
Provides-Extra: bcrypt
Requires-Dist: asyncssh[bcrypt]; extra == "bcrypt"
Provides-Extra: fido2
Requires-Dist: asyncssh[fido2]; extra == "fido2"
Provides-Extra: gssapi
Requires-Dist: asyncssh[gssapi]; extra == "gssapi"
Provides-Extra: libnacl
Requires-Dist: asyncssh[libnacl]; extra == "libnacl"
Provides-Extra: pkcs11
Requires-Dist: asyncssh[python-pkcs11]; extra == "pkcs11"
Provides-Extra: pyopenssl
Requires-Dist: asyncssh[pyOpenSSL]; extra == "pyopenssl"
Provides-Extra: pywin32
Requires-Dist: asyncssh[pywin32]; extra == "pywin32"
